mft2parquet/README.MD
mft2parquet/__init__.py
mft2parquet/requirements.txt
mft2parquet/thirdparty.json
mft2parquet/uffs.com
mft2parquet-0.11.dist-info/LICENSE.rst
mft2parquet-0.11.dist-info/METADATA
mft2parquet-0.11.dist-info/WHEEL
mft2parquet-0.11.dist-info/top_level.txt
mft2parquet-0.11.dist-info/RECORD
