Metadata-Version: 2.1
Name: mft2parquet
Version: 0.11
Summary: mft to parquet (pyarrow dtypes)
Home-page: https://github.com/hansalemaos/mft2parquet
Author: Johannes Fischer
Author-email: aulasparticularesdealemaosp@gmail.com
License: MIT
Keywords: mft,file,search
Classifier: Development Status :: 4 - Beta
Classifier: Programming Language :: Python :: 3 :: Only
Classifier: Programming Language :: Python :: 3.10
Classifier: Topic :: Software Development :: Libraries :: Python Modules
Classifier: Topic :: Utilities
License-File: LICENSE.rst
Requires-Dist: getfilenuitkapython
Requires-Dist: pandas
Requires-Dist: touchtouch
